reiuji/__init__.py
reiuji/components/__init__.py
reiuji/components/base.py
reiuji/components/types.py
reiuji/components/defaults/__init__.py
reiuji/components/defaults/accelerator.py
reiuji/components/defaults/nucleosynthesis.py
reiuji/components/defaults/turbine.py
reiuji/core/__init__.py
reiuji/core/multi_sequence.py
reiuji/designer/__init__.py
reiuji/designer/base/__init__.py
reiuji/designer/base/calculations.py
reiuji/designer/base/constraints.py
reiuji/designer/base/designer.py
reiuji/designer/base/placement_rules.py
reiuji/designer/base/scaled_calculations.py
reiuji/designer/overhauled/__init__.py
reiuji/designer/overhauled/turbine_dynamo/__init__.py
reiuji/designer/overhauled/turbine_dynamo/calculations.py
reiuji/designer/overhauled/turbine_dynamo/constraints.py
reiuji/designer/overhauled/turbine_dynamo/designer.py
reiuji/designer/overhauled/turbine_rotor/__init__.py
reiuji/designer/overhauled/turbine_rotor/calculations.py
reiuji/designer/overhauled/turbine_rotor/designer.py
reiuji/designer/qmd/__init__.py
reiuji/designer/qmd/decelerator/__init__.py
reiuji/designer/qmd/decelerator/constraints.py
reiuji/designer/qmd/decelerator/designer.py
reiuji/designer/qmd/linear/__init__.py
reiuji/designer/qmd/linear/calculations.py
reiuji/designer/qmd/linear/constraints.py
reiuji/designer/qmd/linear/designer.py
reiuji/designer/qmd/nucleosynthesis/__init__.py
reiuji/designer/qmd/nucleosynthesis/calculations.py
reiuji/designer/qmd/nucleosynthesis/constraints.py
reiuji/designer/qmd/nucleosynthesis/designer.py
reiuji/designer/qmd/synchrotron/__init__.py
reiuji/designer/qmd/synchrotron/calculations.py
reiuji/designer/qmd/synchrotron/constraints.py
reiuji/designer/qmd/synchrotron/designer.py
reiuji/io/__init__.py
reiuji/io/serialization.py
reiuji/io/schematics/__init__.py
reiuji/io/schematics/accelerator.py
reiuji/io/schematics/base.py
reiuji/io/schematics/nucleosynthesis.py
reiuji/io/schematics/turbine.py
reiuji_nuclearcraft-0.1.1.dist-info/LICENSE
reiuji_nuclearcraft-0.1.1.dist-info/METADATA
reiuji_nuclearcraft-0.1.1.dist-info/WHEEL
reiuji_nuclearcraft-0.1.1.dist-info/top_level.txt
reiuji_nuclearcraft-0.1.1.dist-info/RECORD
