Metadata-Version: 2.1
Name: reiuji_nuclearcraft
Version: 0.1.1
Summary: A library for designing NuclearCraft multiblocks.
Author-email: Celeste Ma <mtcelestema@proton.me>
License: Apache License
Project-URL: Homepage, https://github.com/MtCelesteMa/reiuji
Project-URL: Repository, https://github.com/MtCelesteMa/reiuji
Project-URL: Bug Tracker, https://github.com/MtCelesteMa/reiuji/issues
Keywords: nuclearcraft,multiblock,design,minecraft
Classifier: Development Status :: 4 - Beta
Classifier: Intended Audience :: Other Audience
Classifier: Topic :: Games/Entertainment
Classifier: License :: OSI Approved :: Apache Software License
Classifier: Programming Language :: Python :: 3.12
Requires-Python: >=3.12
License-File: LICENSE
Requires-Dist: pydantic
Requires-Dist: ortools
Requires-Dist: nbt
